<?xml version="1.0" encoding="utf-8"?>
<nrml xmlns:gml="http://www.opengis.net/gml" xmlns="http://openquake.org/xmlns/nrml/0.4">
    <singlePlaneRupture>
        <magnitude>4.9</magnitude>
        <rake>98</rake>
        <hypocenter lat="49.28" lon="-123.34" depth="5"/>
        <planarSurface strike="262" dip="47">
            <topLeft lon="-123.32033" lat="49.27404" depth="4.08357"/>
            <topRight lon="-123.35639" lat="49.27073" depth="4.08357"/>
            <bottomLeft lon="-123.32360" lat="49.28926" depth="5.91643"/>
            <bottomRight lon="-123.35968" lat="49.28596" depth="5.91643"/>
        </planarSurface>
    </singlePlaneRupture>
</nrml>
