<?xml version='1.0' encoding='utf-8'?>
<nrml xmlns:gml="http://www.opengis.net/gml" xmlns="http://openquake.org/xmlns/nrml/0.4">
    <singlePlaneRupture>
        <magnitude>6.9</magnitude>
        <rake>98.0</rake>
        <hypocenter lat="49.2428" lon="-123.6266" depth="3" />
        <planarSurface dip="47.0" strike="262.0">
            <topLeft lon="-123.36073823097252" lat="49.24147033410063" depth="0.0" />
            <topRight lon="-123.88150008510445" lat="49.1937146758729" depth="0.0" />
            <bottomLeft lon="-123.38187667819304" lat="49.3420843266313" depth="12.109534918132784" />
            <bottomRight lon="-123.90368007922253" lat="49.29423122919682" depth="12.109534918132784" />
        </planarSurface>
    </singlePlaneRupture>
</nrml>
